labfreed/__init__.py
labfreed/labfreed_infrastructure.py
labfreed/pac_cat/__init__.py
labfreed/pac_cat/category_base.py
labfreed/pac_cat/pac_cat.py
labfreed/pac_cat/predefined_categories.py
labfreed/pac_id/__init__.py
labfreed/pac_id/extension.py
labfreed/pac_id/id_segment.py
labfreed/pac_id/pac_id.py
labfreed/pac_id/url_parser.py
labfreed/pac_id/url_serializer.py
labfreed/pac_id_resolver/__init__.py
labfreed/pac_id_resolver/cit_common.py
labfreed/pac_id_resolver/cit_v1.py
labfreed/pac_id_resolver/cit_v2.py
labfreed/pac_id_resolver/resolver.py
labfreed/pac_id_resolver/services.py
labfreed/qr/__init__.py
labfreed/qr/generate_qr.py
labfreed/trex/__init__.py
labfreed/trex/table_segment.py
labfreed/trex/trex.py
labfreed/trex/trex_base_models.py
labfreed/trex/value_segments.py
labfreed/trex/python_convenience/__init__.py
labfreed/trex/python_convenience/data_table.py
labfreed/trex/python_convenience/pyTREX.py
labfreed/trex/python_convenience/quantity.py
labfreed/utilities/base36.py
labfreed/well_known_extensions/__init__.py
labfreed/well_known_extensions/default_extension_interpreters.py
labfreed/well_known_extensions/display_name_extension.py
labfreed/well_known_extensions/trex_extension.py
labfreed/well_known_keys/gs1/__init__.py
labfreed/well_known_keys/gs1/gs1.py
labfreed/well_known_keys/gs1/gs1_ai_enum_sorted.py
labfreed/well_known_keys/labfreed/well_known_keys.py
labfreed/well_known_keys/unece/UneceUnits.json
labfreed/well_known_keys/unece/__init__.py
labfreed/well_known_keys/unece/unece_units.py
labfreed-0.2.12.dist-info/licenses/LICENSE
labfreed-0.2.12.dist-info/WHEEL
labfreed-0.2.12.dist-info/METADATA
labfreed-0.2.12.dist-info/RECORD
