Metadata-Version: 2.4
Name: labfreed
Version: 0.2.12
Summary: Python implementation of LabFREED building blocks
Author-email: Reto Thürer <thuerer.r@buchi.com>
Requires-Python: >=3.11
Classifier: License :: OSI Approved :: MIT License
Classifier: Programming Language :: Python
Classifier: Programming Language :: Python :: 3
Classifier: Programming Language :: Python :: 3.11
Classifier: Operating System :: OS Independent
Classifier: Development Status :: 4 - Beta
Classifier: Topic :: Scientific/Engineering
Classifier: Topic :: Utilities
Classifier: Intended Audience :: Developers
Classifier: Intended Audience :: Science/Research
License-File: LICENSE
Requires-Dist: numpy>=2.2.4
Requires-Dist: pydantic>=2.11.3
Requires-Dist: segno>=1.6.6
Requires-Dist: typer>=0.15.2
Requires-Dist: PyYAML>=6.0.2
Requires-Dist: jsonpath-ng>=1.7.0
Requires-Dist: requests>=2.32.3
Requires-Dist: requests_cache>=1.2.1
Requires-Dist: pytest>=8.3.5 ; extra == "dev"
Requires-Dist: pdoc>=15.0.1 ; extra == "dev"
Requires-Dist: flit>=3.12.0 ; extra == "dev"
Requires-Dist: ruff>=0.11.5 ; extra == "dev"
Project-URL: Documentation, https://github.com/retothuerer/LabFREED?tab=readme-ov-file#readme
Project-URL: Homepage, https://github.com/retothuerer/LabFREED
Project-URL: Source, https://github.com/retothuerer/LabFREED
Project-URL: Tracker, https://github.com/retothuerer/LabFREED/issues
Provides-Extra: dev
